rachit_madhegaria/__init__.py
rachit_madhegaria-0.1.dist-info/LICENSE.txt
rachit_madhegaria-0.1.dist-info/METADATA
rachit_madhegaria-0.1.dist-info/WHEEL
rachit_madhegaria-0.1.dist-info/top_level.txt
rachit_madhegaria-0.1.dist-info/RECORD
