Metadata-Version: 2.1
Name: rachit-madhegaria
Version: 0.1
Summary: To find the  average of a nxn matrix by separating it into a 2x2 matrix where n is even number
Author: Rachit Madhegaria
Author-email: rachit.20122003@gmail.com
Classifier: Programming Language :: Python :: 3
Classifier: License :: OSI Approved :: MIT License
Classifier: Operating System :: OS Independent
License-File: LICENSE.txt
